lppinv/__init__.py
lppinv/lppinv.py
lppinv-1.0.1.dist-info/licenses/LICENSE
lppinv-1.0.1.dist-info/METADATA
lppinv-1.0.1.dist-info/WHEEL
lppinv-1.0.1.dist-info/top_level.txt
lppinv-1.0.1.dist-info/RECORD
