Metadata-Version: 2.4
Name: lppinv
Version: 1.0.1
Summary: Linear Programming via Pseudoinverse Estimation
Author-email: The Economist <29724411+econcz@users.noreply.github.com>
License-Expression: MIT
Project-URL: Homepage, https://github.com/econcz/lppinv
Project-URL: Bug Tracker, https://github.com/econcz/lppinv/issues
Keywords: linear-programing,convex-optimization,least-squares,generalized-inverse,regularization
Classifier: Programming Language :: Python :: 3
Classifier: Programming Language :: Python :: 3.10
Classifier: Programming Language :: Python :: 3.11
Classifier: Programming Language :: Python :: 3.12
Classifier: Operating System :: OS Independent
Classifier: Topic :: Scientific/Engineering :: Mathematics
Classifier: Topic :: Scientific/Engineering :: Information Analysis
Requires-Python: >=3.10
License-File: LICENSE
Requires-Dist: numpy>=1.24
Requires-Dist: pyclsp>=1.1.2
Dynamic: license-file
